LICENSE.txt
README.rst
setup.py
imena/__init__.py
imena/firstname_female_eng.txt
imena/firstname_female_rus.txt
imena/firstname_female_ukr.txt
imena/firstname_male_eng.txt
imena/firstname_male_rus.txt
imena/firstname_male_ukr.txt
imena/lastname_female_eng.txt
imena/lastname_female_rus.txt
imena/lastname_female_ukr.txt
imena/lastname_male_eng.txt
imena/lastname_male_rus.txt
imena/lastname_male_ukr.txt
imena/otch_female_rus.txt
imena/otch_female_ukr.txt
imena/otch_male_rus.txt
imena/otch_male_ukr.txt
r00_Imena.egg-info/PKG-INFO
r00_Imena.egg-info/SOURCES.txt
r00_Imena.egg-info/dependency_links.txt
r00_Imena.egg-info/top_level.txt
r00_imena.egg-info/PKG-INFO
r00_imena.egg-info/SOURCES.txt
r00_imena.egg-info/dependency_links.txt
r00_imena.egg-info/top_level.txt